odoo/addons/pos_bank_statement_line_no_change/README.rst
odoo/addons/pos_bank_statement_line_no_change/__init__.py
odoo/addons/pos_bank_statement_line_no_change/__manifest__.py
odoo/addons/pos_bank_statement_line_no_change/i18n/fr.po
odoo/addons/pos_bank_statement_line_no_change/i18n/it.po
odoo/addons/pos_bank_statement_line_no_change/i18n/pos_bank_statement_line_no_change.pot
odoo/addons/pos_bank_statement_line_no_change/models/__init__.py
odoo/addons/pos_bank_statement_line_no_change/models/account_bank_statement_line.py
odoo/addons/pos_bank_statement_line_no_change/readme/CONTRIBUTORS.rst
odoo/addons/pos_bank_statement_line_no_change/readme/DESCRIPTION.rst
odoo/addons/pos_bank_statement_line_no_change/static/description/icon.png
odoo/addons/pos_bank_statement_line_no_change/static/description/index.html
odoo/addons/pos_bank_statement_line_no_change/tests/__init__.py
odoo/addons/pos_bank_statement_line_no_change/tests/test_module.py
odoo12_addon_pos_bank_statement_line_no_change-12.0.1.0.1.99.dev5.dist-info/METADATA
odoo12_addon_pos_bank_statement_line_no_change-12.0.1.0.1.99.dev5.dist-info/WHEEL
odoo12_addon_pos_bank_statement_line_no_change-12.0.1.0.1.99.dev5.dist-info/top_level.txt
odoo12_addon_pos_bank_statement_line_no_change-12.0.1.0.1.99.dev5.dist-info/RECORD
